{
  "_class": "artboard",
  "backgroundColor": {
    "_class": "color",
    "alpha": 1,
    "blue": 0.9725,
    "green": 0.9647,
    "red": 0.9569
  },
  "do_objectID": "1686E748-C363-4329-8909-7E386C9A6754",
  "exportOptions": {
    "_class": "exportOptions",
    "exportFormats": [
      {
        "_class": "exportFormat",
        "absoluteSize": 0,
        "fileFormat": "png",
        "name": "",
        "namingScheme": 0,
        "scale": 1,
        "visibleScaleType": 0
      }
    ],
    "includedLayerIds": [
    ],
    "layerOptions": 0,
    "shouldTrim": false
  },
  "frame": {
    "_class": "rect",
    "constrainProportions": false,
    "height": 950,
    "width": 294,
    "x": 0,
    "y": 390
  },
  "hasBackgroundColor": true,
  "hasClickThrough": false,
  "horizontalRulerData": {
    "_class": "rulerData",
    "base": 0,
    "guides": [
    ]
  },
  "includeBackgroundColorInExport": true,
  "includeInCloudUpload": true,
  "isFlippedHorizontal": false,
  "isFlippedVertical": false,
  "isLocked": false,
  "isVisible": true,
  "layerListExpandedType": 0,
  "layers": [
    {
      "class": "group",
      "id": "78522D97-060A-41BB-B828-19AA03792B7A"
    },
    {
      "class": "group",
      "id": "B7086CC8-2F99-464B-A323-47B66E40BFE5"
    },
    {
      "class": "group",
      "id": "69F865F8-B049-4790-A156-1E790AA40BB0"
    },
    {
      "class": "text",
      "id": "6C66329C-8857-4040-A624-6F591D33F2D3"
    }
  ],
  "name": "🖥 Table of contents",
  "nameIsFixed": false,
  "resizesContent": false,
  "resizingConstraint": 63,
  "resizingType": 0,
  "rotation": 0,
  "shouldBreakMaskChain": false,
  "style": {
    "_class": "style",
    "endDecorationType": 0,
    "miterLimit": 10,
    "startDecorationType": 0
  },
  "userInfo": {
    "com.animaapp.stc-sketch-plugin": {
      "kModelPropertiesKey": {
      }
    }
  },
  "verticalRulerData": {
    "_class": "rulerData",
    "base": 0,
    "guides": [
    ]
  }
}