{
  "_class": "shapeGroup",
  "clippingMaskMode": 0,
  "do_objectID": "C40791B2-1C4E-4D47-B6F3-1BDFF15A1DBD",
  "exportOptions": {
    "_class": "exportOptions",
    "exportFormats": [
    ],
    "includedLayerIds": [
    ],
    "layerOptions": 0,
    "shouldTrim": false
  },
  "frame": {
    "_class": "rect",
    "constrainProportions": true,
    "height": 16,
    "width": 16,
    "x": 0,
    "y": 0
  },
  "hasClickThrough": false,
  "hasClippingMask": false,
  "isFlippedHorizontal": false,
  "isFlippedVertical": false,
  "isLocked": false,
  "isVisible": true,
  "layerListExpandedType": 0,
  "layers": [
    {
      "class": "rectangle",
      "id": "DCBDF971-47A0-4710-A5BF-9384E4735215"
    }
  ],
  "name": "Rectangle 3",
  "nameIsFixed": false,
  "originalObjectID": "802A0999-FC23-43C1-8BD8-8E3A8688B46E",
  "resizingConstraint": 63,
  "resizingType": 0,
  "rotation": 0,
  "shouldBreakMaskChain": false,
  "style": {
    "sharedObjectID": "10C00C80-9DA3-42A1-A21A-EC0CCEA46520"
  },
  "userInfo": {
    "com.animaapp.stc-sketch-plugin": {
      "kModelPropertiesKey": {
        "constraints": {
          "aspectRatio": {
            "constant": 16,
            "enabled": 1,
            "modelID": "constraint_91ba77e8-3fa2-4e33-957d-0da990309cc2",
            "model_class": "ADModelConstraint",
            "model_version": 0.1,
            "multiplier": 16
          },
          "automatic": 1,
          "modelID": "viewConstraints_c256edff-df73-4f7b-bb29-620ecf757387",
          "model_class": "ADModelViewConstraints",
          "model_version": 0.1
        }
      }
    }
  },
  "windingRule": 1
}