{
  "_class": "group",
  "do_objectID": "EBFCAAC2-4D1D-49AE-ABA7-DFECEBC00941",
  "exportOptions": {
    "_class": "exportOptions",
    "exportFormats": [
    ],
    "includedLayerIds": [
    ],
    "layerOptions": 0,
    "shouldTrim": false
  },
  "frame": {
    "_class": "rect",
    "constrainProportions": false,
    "height": 36,
    "width": 151,
    "x": 61,
    "y": 211
  },
  "hasClickThrough": false,
  "isFlippedHorizontal": false,
  "isFlippedVertical": false,
  "isLocked": false,
  "isVisible": true,
  "layerListExpandedType": 0,
  "layers": [
    {
      "class": "shapeGroup",
      "id": "5F9A3702-8980-4912-A4A3-90764AB4AA47"
    },
    {
      "class": "text",
      "id": "994FD8FD-9E89-416C-8AF8-049DCBF82575"
    }
  ],
  "name": "Button - outline",
  "nameIsFixed": true,
  "resizingConstraint": 33,
  "resizingType": 1,
  "rotation": 0,
  "shouldBreakMaskChain": false,
  "style": {
    "_class": "style",
    "endDecorationType": 0,
    "miterLimit": 10,
    "startDecorationType": 0
  },
  "userInfo": {
    "com.animaapp.stc-sketch-plugin": {
      "kModelPropertiesKey": {
      }
    }
  }
}