{
  "_class": "group",
  "do_objectID": "01046BB7-29E5-48F2-9CB8-2CBFC7963F9C",
  "exportOptions": {
    "_class": "exportOptions",
    "exportFormats": [
    ],
    "includedLayerIds": [
    ],
    "layerOptions": 0,
    "shouldTrim": false
  },
  "frame": {
    "_class": "rect",
    "constrainProportions": false,
    "height": 200,
    "width": 1580,
    "x": 36,
    "y": 45
  },
  "hasClickThrough": true,
  "isFlippedHorizontal": false,
  "isFlippedVertical": false,
  "isLocked": false,
  "isVisible": true,
  "layerListExpandedType": 0,
  "layers": [
    {
      "class": "group",
      "id": "8C97F5DF-D695-4C24-B159-B5E23F9510A0"
    },
    {
      "class": "group",
      "id": "BD0B26A4-AA5D-426B-B9D9-C28CDEB8600F"
    },
    {
      "class": "group",
      "id": "7F8AA958-C2AD-4D19-96D8-FA5925A5D8CB"
    },
    {
      "class": "group",
      "id": "EDD5F2B8-E82A-4FA2-AC16-916519B5E662"
    },
    {
      "class": "group",
      "id": "5087CCAA-5E9B-4E50-86E4-6BFE73324C59"
    },
    {
      "class": "group",
      "id": "B9AC0B3F-9307-4813-8573-A798C60BB08B"
    },
    {
      "class": "group",
      "id": "CABA77EF-AB4F-426F-B19E-F00EE6016AB1"
    },
    {
      "class": "group",
      "id": "C8770041-A752-4439-93CE-E6B15F3BB900"
    },
    {
      "class": "group",
      "id": "6E5AA02B-18E7-4BE3-8523-1B3C6150E768"
    },
    {
      "class": "group",
      "id": "040E98D0-8E33-4A89-B671-3EE3DF1F0385"
    }
  ],
  "name": "Stacked Group",
  "nameIsFixed": false,
  "resizingConstraint": 63,
  "resizingType": 0,
  "rotation": 0,
  "shouldBreakMaskChain": false,
  "style": {
    "_class": "style",
    "endDecorationType": 0,
    "miterLimit": 10,
    "startDecorationType": 0
  },
  "userInfo": {
    "com.animaapp.stc-sketch-plugin": {
      "kModelPropertiesKey": {
        "align": 5,
        "spacing": 0,
        "type": 1
      },
      "kViewTypeKey": "ADModelStackView"
    }
  }
}